{
    ":0000000d": {
        "cpu": 694.046066,
        "name": "snlua event/service/main",
        "mqlen": 0,
        "memory": "37662.93 Kb",
        "message": 231410,
        "task": 6
    },
    ":00000006": {
        "cpu": 0.034997,
        "name": "snlua datacenterd",
        "mqlen": 0,
        "memory": "632.67 Kb",
        "message": 8,
        "task": 0
    },
    ":0000000c": {
        "cpu": 1942.397654,
        "name": "snlua sensor/service/main",
        "mqlen": 0,
        "memory": "28388.33 Kb",
        "message": 490379,
        "task": 3
    },
    ":00000007": {
        "cpu": 0.042409,
        "name": "snlua service_mgr",
        "mqlen": 0,
        "memory": "677.30 Kb",
        "message": 25,
        "task": 1
    },
    ":00000008": {
        "cpu": 0.256893,
        "name": "snlua hica/subsys/alarm/service/main",
        "mqlen": 0,
        "memory": "469.23 Kb",
        "message": 140,
        "task": 1
    },
    ":00000004": {
        "cpu": 0.038833,
        "name": "snlua cdummy",
        "mqlen": 0,
        "memory": "637.85 Kb",
        "message": 14,
        "task": 0
    },
    ":0000000a": {
        "cpu": 15.832671,
        "name": "snlua harbor",
        "mqlen": 0,
        "memory": "923.62 Kb",
        "message": 43762,
        "task": 2
    },
    ":0000000f": {
        "cpu": 104.092848,
        "name": "snlua frudata/service/main",
        "mqlen": 0,
        "memory": "13974.14 Kb",
        "message": 105928,
        "task": 4
    },
    ":00000009": {
        "cpu": 0.096192,
        "name": "snlua sd_bus",
        "mqlen": 0,
        "memory": "655.75 Kb",
        "message": 14,
        "task": 0
    },
    ":0000000e": {
        "cpu": 43.882965,
        "name": "snlua host_agent/service/main",
        "mqlen": 0,
        "memory": "4013.86 Kb",
        "message": 77142,
        "task": 3
    },
    ":0000000b": {
        "cpu": 0.039453,
        "name": "snlua debug_console 0.0.0.0 40023",
        "mqlen": 0,
        "memory": "726.34 Kb",
        "message": 10,
        "task": 0
    }
}